fortigate_cert_decoder/__init__.py
fortigate_cert_decoder/cert_decode.py
fortigate_cert_decoder-1.0.1.dist-info/licenses/LICENSE
fortigate_cert_decoder-1.0.1.dist-info/METADATA
fortigate_cert_decoder-1.0.1.dist-info/WHEEL
fortigate_cert_decoder-1.0.1.dist-info/entry_points.txt
fortigate_cert_decoder-1.0.1.dist-info/top_level.txt
fortigate_cert_decoder-1.0.1.dist-info/RECORD
