Metadata-Version: 2.4
Name: fortigate-cert-decoder
Version: 1.0.1
Summary: A CLI tool for retrieving and decoding certificates from FortiGate devices
Home-page: https://github.com/yourusername/fortigate-cert-decoder
Author: Todd Albiston
Author-email: Todd Albiston <foxtrot711@gmail.com>
Project-URL: Homepage, https://github.com/yourusername/fortigate-cert-decoder
Project-URL: Bug Reports, https://github.com/yourusername/fortigate-cert-decoder/issues
Project-URL: Source, https://github.com/yourusername/fortigate-cert-decoder
Keywords: fortigate,certificate,ssl,tls,decoder,x509,firewall
Classifier: Development Status :: 4 - Beta
Classifier: Intended Audience :: System Administrators
Classifier: Topic :: System :: Networking :: Firewalls
Classifier: Topic :: Security
Classifier: License :: OSI Approved :: MIT License
Classifier: Programming Language :: Python :: 3
Classifier: Programming Language :: Python :: 3.7
Classifier: Programming Language :: Python :: 3.8
Classifier: Programming Language :: Python :: 3.9
Classifier: Programming Language :: Python :: 3.10
Classifier: Programming Language :: Python :: 3.11
Classifier: Operating System :: OS Independent
Requires-Python: >=3.7
License-File: LICENSE
Requires-Dist: requests>=2.28.0
Requires-Dist: cryptography>=41.0.0
Requires-Dist: rich>=13.0.0
Requires-Dist: urllib3>=1.26.0
Dynamic: author
Dynamic: home-page
Dynamic: license-file
Dynamic: requires-python
